README.rst
setup.py
vaneska/__init__.py
vaneska/models.py
vaneska/photometry.py
vaneska.egg-info/PKG-INFO
vaneska.egg-info/SOURCES.txt
vaneska.egg-info/dependency_links.txt
vaneska.egg-info/requires.txt
vaneska.egg-info/top_level.txt