Metadata-Version: 1.1
Name: vaneska
Version: 0.0.dev0
Summary: Sweet PSF photometry tool for TESS
Home-page: https://github.com/mirca/vaneska
Author: mirca
Author-email: jvmirca@gmail.com
License: MIT
Keywords: statistics probability
Platform: UNKNOWN
Classifier: Development Status :: 3 - Alpha
Classifier: Intended Audience :: Science/Research
Classifier: License :: OSI Approved :: MIT License
Classifier: Programming Language :: Python :: 3.6
